check_certs/__init__.py
check_certs/check_certs.py
check_certs/utils.py
check_certs/plugins/__init__.py
check_certs/plugins/irc_notifier.py
check_certs/plugins/ses_notifier.py
check_certs/tests/__init__.py
check_certs/tests/test_check_certs.py
check_certs/tests/test_utils.py
check_certs-0.1.8.dist-info/LICENSE.txt
check_certs-0.1.8.dist-info/METADATA
check_certs-0.1.8.dist-info/WHEEL
check_certs-0.1.8.dist-info/entry_points.txt
check_certs-0.1.8.dist-info/top_level.txt
check_certs-0.1.8.dist-info/RECORD
